variable_updater/__init__.py
variable_updater/__main__.py
variable_updater/bitbucket_requester.py
variable_updater/bitbucket_variable.py
variable_updater/cli.py
variable_updater/config_file.py
variable_updater/environment_variables.py
variable_updater/variable_updater.py
variable_updater/vault.py
variable_updater/version.py
variable_updater-0.0.16.dist-info/entry_points.txt
variable_updater-0.0.16.dist-info/WHEEL
variable_updater-0.0.16.dist-info/METADATA
variable_updater-0.0.16.dist-info/RECORD
